PYLIQ/PYLIQ_functions.py
PYLIQ/__init__.py
PYLIQ-1.0.1.dist-info/LICENSE
PYLIQ-1.0.1.dist-info/METADATA
PYLIQ-1.0.1.dist-info/WHEEL
PYLIQ-1.0.1.dist-info/top_level.txt
PYLIQ-1.0.1.dist-info/RECORD
