Metadata-Version: 2.1
Name: PYLIQ
Version: 1.0.1
Summary: Free soil liquefaction analysis software from SPT data
Home-page: https://github.com/jorge243/PYLIQ
Author: Jorge Ordóñez
Author-email: jorgeordonezr@gmail.com
License: ['MIT']
Platform: UNKNOWN
